CHANGELOG.txt
LICENCE.txt
LICENSE
MANIFEST.in
PyVM
README.txt
__init__.py
setup.py
PyVM/PyVM.py
PyVM/__init__.py
PyVM/test.py
PyVM.egg-info/PKG-INFO
PyVM.egg-info/SOURCES.txt
PyVM.egg-info/dependency_links.txt
PyVM.egg-info/top_level.txt