Metadata-Version: 1.1
Name: PyVM
Version: 0.0.2
Summary:  Python for operation between vector and matrix
Home-page: UNKNOWN
Author: D.Fathi
Author-email: Dhiabi.Fathi@gmail.com
License: MIT
Keywords: PyVM
Platform: UNKNOWN
Classifier: Development Status :: 1 - Planning
Classifier: Intended Audience :: Education
Classifier: License :: OSI Approved :: MIT License
Classifier: Programming Language :: Python :: 3
